LICENSE
MANIFEST.in
README.rst
requirements.txt
setup.py
version.py
alignak_checks_windows_nsca/__init__.py
alignak_checks_windows_nsca.egg-info/PKG-INFO
alignak_checks_windows_nsca.egg-info/SOURCES.txt
alignak_checks_windows_nsca.egg-info/dependency_links.txt
alignak_checks_windows_nsca.egg-info/not-zip-safe
alignak_checks_windows_nsca.egg-info/top_level.txt
alignak_checks_windows_nsca/etc/arbiter/packs/resource.d/windows-nsca.cfg
alignak_checks_windows_nsca/etc/arbiter/packs/windows-nsca/groups.cfg
alignak_checks_windows_nsca/etc/arbiter/packs/windows-nsca/hosts.cfg
alignak_checks_windows_nsca/etc/arbiter/packs/windows-nsca/services.cfg
alignak_checks_windows_nsca/etc/arbiter/packs/windows-nsca/templates.cfg
alignak_checks_windows_nsca/json/windows-nsca/hostgroups.json
alignak_checks_windows_nsca/json/windows-nsca/hosts-templates.json
alignak_checks_windows_nsca/json/windows-nsca/servicegroups.json
alignak_checks_windows_nsca/json/windows-nsca/services-templates.json
alignak_checks_windows_nsca/json/windows-nsca/setup.sh