Metadata-Version: 1.1
Name: alignak-checks-windows-nsca
Version: 1.0.0
Summary: Alignak checks pack for Windows NSCA monitored hosts
Home-page: https://github.com/Alignak-monitoring-contrib/alignak-checks-windows-nsca
Author: Frédéric MOHIER
Author-email: frederic.mohier@alignak.net
License: GNU Affero General Public License, version 3
Keywords: a,l,i,g,n,a,k, ,m,o,n,i,t,o,r,i,n,g, ,p,a,c,k, ,c,h,e,c,k,s, ,w,i,n,d,o,w,s,-,n,s,c,a
Platform: UNKNOWN
Classifier: Development Status :: 5 - Production/Stable
Classifier: Environment :: Console
Classifier: Intended Audience :: Developers
Classifier: Intended Audience :: System Administrators
Classifier: License :: OSI Approved :: GNU Affero General Public License v3 or later (AGPLv3+)
Classifier: Natural Language :: English
Classifier: Programming Language :: Python
Classifier: Topic :: System :: Monitoring
Classifier: Topic :: System :: Systems Administration
